ksl_util/__init__.py
ksl_util/evaluation/__init__.py
ksl_util/evaluation/delong/__init__.py
ksl_util/evaluation/metric/__init__.py
ksl_util/evaluation/metric/evaluate.py
ksl_util/file/__init__.py
ksl_util/file/directory/__init__.py
ksl_util/file/directory/directory_manager.py
ksl_util/file/image/ImageReader.py
ksl_util/file/image/IoU.py
ksl_util/file/image/__init__.py
ksl_util/file/image/heat_map_generate.py
ksl_util/file/image/image_loader.py
ksl_util/file/image/image_variation.py
ksl_util/file/image/tif_manager.py
ksl_util/log/__init__.py
ksl_util/logic/__init__.py
ksl_util/text/__init__.py
ksl_util/text/sha256.py
ksl_util/text/translator.py
ksl_util/time/__init__.py
ksl_util/time/time_check.py
ksl_util-0.0.1.dist-info/METADATA
ksl_util-0.0.1.dist-info/WHEEL
ksl_util-0.0.1.dist-info/top_level.txt
ksl_util-0.0.1.dist-info/RECORD
