Metadata-Version: 2.1
Name: ksl-util
Version: 0.0.1
Summary: ksl_util
Home-page: UNKNOWN
Author: Kyungsu Lee
Author-email: ks_lee@dgist.ac.kr
License: UNKNOWN
Platform: UNKNOWN
Classifier: Programming Language :: Python :: 3
Classifier: License :: OSI Approved :: MIT License
Classifier: Operating System :: OS Independent
Requires-Python: >=3.6
